hgvs_dataproviders_rest/__init__.py
hgvs_dataproviders_rest/restapi.py
hgvs_dataproviders_rest/restclient.py
hgvs_dataproviders_rest-0.0.2.dist-info/LICENSE
hgvs_dataproviders_rest-0.0.2.dist-info/METADATA
hgvs_dataproviders_rest-0.0.2.dist-info/WHEEL
hgvs_dataproviders_rest-0.0.2.dist-info/top_level.txt
hgvs_dataproviders_rest-0.0.2.dist-info/zip-safe
hgvs_dataproviders_rest-0.0.2.dist-info/RECORD
