Metadata-Version: 2.1
Name: hgvs-dataproviders-rest
Version: 0.0.2
Summary: hgvs dataproviders based on UTA and SeqRepo REST Interfaces
Author-email: Reece Hart <reece@myome.com>, Caitlin Gong <caitlin.gong@myome.com>
Project-URL: Homepage, https://github.com/biocommons/hgvs-dataproviders-rest
Project-URL: Bug Tracker, https://github.com/biocommons/hgvs-dataproviders-rest/issues
Classifier: Programming Language :: Python :: 3
Classifier: Programming Language :: Python :: 3.8
Classifier: Programming Language :: Python :: 3.9
Classifier: Programming Language :: Python :: 3.10
Classifier: License :: OSI Approved :: MIT License
Classifier: Operating System :: OS Independent
Requires-Python: >=3.8
License-File: LICENSE
Requires-Dist: coloredlogs (~=15.0)
Requires-Dist: pyyaml (~=6.0)
Requires-Dist: fastapi
Requires-Dist: pydantic
Requires-Dist: uvicorn
Requires-Dist: hgvs
Provides-Extra: dev
Requires-Dist: bandit (~=1.7) ; extra == 'dev'
Requires-Dist: black (~=22.3) ; extra == 'dev'
Requires-Dist: build (~=0.8) ; extra == 'dev'
Requires-Dist: flake8 (~=4.0) ; extra == 'dev'
Requires-Dist: ipython (~=8.4) ; extra == 'dev'
Requires-Dist: isort (~=5.10) ; extra == 'dev'
Requires-Dist: mypy ; extra == 'dev'
Requires-Dist: pylint (~=2.14) ; extra == 'dev'
Requires-Dist: pre-commit ; extra == 'dev'
Provides-Extra: docs
Requires-Dist: mkdocs ; extra == 'docs'
Provides-Extra: test
Requires-Dist: pytest (~=7.1) ; extra == 'test'
Requires-Dist: pytest-cov (~=4.0) ; extra == 'test'
Requires-Dist: pytest-optional-tests ; extra == 'test'
Requires-Dist: tox (~=3.25) ; extra == 'test'
Requires-Dist: vcrpy ; extra == 'test'
Requires-Dist: pytest-vcr ; extra == 'test'
